keycloak_srvcloud/__init__.py
keycloak_srvcloud/base_keycloak.py
keycloak_srvcloud-0.0.1.dist-info/METADATA
keycloak_srvcloud-0.0.1.dist-info/WHEEL
keycloak_srvcloud-0.0.1.dist-info/top_level.txt
keycloak_srvcloud-0.0.1.dist-info/RECORD
