Metadata-Version: 2.1
Name: keycloak-srvcloud
Version: 0.0.1
Summary: Lib for interacting with keycloak from srvCloud
Home-page: https://github.com/VITca64rus/keycloak_srvcloud.git
Author: vitca64rus
Author-email: vitca64rus@gmail.com
License: UNKNOWN
Project-URL: GitHub, https://github.com/VITca64rus/keycloak_srvcloud.git
Keywords: files speedfiles
Platform: UNKNOWN
Classifier: Programming Language :: Python :: 3.11
Classifier: License :: OSI Approved :: MIT License
Classifier: Operating System :: OS Independent
Requires-Python: >=3.6
Requires-Dist: requests (>=2.25.1)
